celium_collateral_contracts/__init__.py
celium_collateral_contracts/abi.json
celium_collateral_contracts/address_conversion.py
celium_collateral_contracts/associate_evm_key.py
celium_collateral_contracts/backup_state.py
celium_collateral_contracts/collateral_contract.py
celium_collateral_contracts/common.py
celium_collateral_contracts/deny_request.py
celium_collateral_contracts/deposit_collateral.py
celium_collateral_contracts/finalize_reclaim.py
celium_collateral_contracts/generate_commands.py
celium_collateral_contracts/generate_keypair.py
celium_collateral_contracts/get_all_associations.py
celium_collateral_contracts/get_balance.py
celium_collateral_contracts/get_collaterals.py
celium_collateral_contracts/get_current_block.py
celium_collateral_contracts/get_executor_collateral.py
celium_collateral_contracts/get_hotkey_association.py
celium_collateral_contracts/get_reclaim_requests.py
celium_collateral_contracts/h160_to_ss58.py
celium_collateral_contracts/list_contracts.py
celium_collateral_contracts/reclaim_collateral.py
celium_collateral_contracts/send_to_ss58_precompile.py
celium_collateral_contracts/setup_evm.py
celium_collateral_contracts/slash_collateral.py
celium_collateral_contracts/subtensor.py
celium_collateral_contracts/verify_contract.py
celium_collateral_contracts-1.0.63.dist-info/licenses/LICENSE
celium_collateral_contracts-1.0.63.dist-info/METADATA
celium_collateral_contracts-1.0.63.dist-info/WHEEL
celium_collateral_contracts-1.0.63.dist-info/top_level.txt
celium_collateral_contracts-1.0.63.dist-info/RECORD
